LICENSE
MANIFEST.in
README.rst
helga_winks.py
setup.py
helga_winks.egg-info/PKG-INFO
helga_winks.egg-info/SOURCES.txt
helga_winks.egg-info/dependency_links.txt
helga_winks.egg-info/entry_points.txt
helga_winks.egg-info/top_level.txt
helga_winks.egg-info/zip-safe