Metadata-Version: 1.1
Name: helga-winks
Version: 1.1.0
Summary: winks @ u
Home-page: https://github.com/michaelorr/helga-winks
Author: Michael Orr
Author-email: michael@orr.co
License: LICENSE
Keywords: irc bot winks
Platform: UNKNOWN
Classifier: Development Status :: 4 - Beta
Classifier: License :: OSI Approved :: GNU General Public License v3 (GPLv3)
Classifier: Operating System :: OS Independent
Classifier: Programming Language :: Python
Classifier: Topic :: Software Development :: Libraries :: Python Modules
Classifier: Topic :: Communications :: Chat :: Internet Relay Chat
